pdf_pro/__init__.py
pdf_pro/main.py
mcp_pdf_pro-0.1.0.dist-info/METADATA
mcp_pdf_pro-0.1.0.dist-info/WHEEL
mcp_pdf_pro-0.1.0.dist-info/entry_points.txt
mcp_pdf_pro-0.1.0.dist-info/RECORD
