Metadata-Version: 2.4
Name: mcp-pdf-pro
Version: 0.1.0
Summary: 基于智谱 GLM-4V 的 PDF 视觉分析 MCP 工具
Author-email: Your Name <your@email.com>
Requires-Python: >=3.10
Requires-Dist: fastmcp
Requires-Dist: openai>=1.0.0
Requires-Dist: pymupdf>=1.23.0
Requires-Dist: python-dotenv
